{"pistol-d1": {

"$down_firing-1":
{
	"frame": {"x":0,"y":0,"w":160,"h":160},
	"rotated": false,
	"trimmed": false,
	"spriteSourceSize": {"x":0,"y":0,"w":160,"h":160},
	"sourceSize": {"w":160,"h":160},
	"pivot": {"x":0.5,"y":0.5}
},
"$down_firing-2":
{
	"frame": {"x":0,"y":160,"w":160,"h":160},
	"rotated": false,
	"trimmed": false,
	"spriteSourceSize": {"x":0,"y":0,"w":160,"h":160},
	"sourceSize": {"w":160,"h":160},
	"pivot": {"x":0.5,"y":0.5}
},
"$down_firing-3":
{
	"frame": {"x":0,"y":320,"w":160,"h":160},
	"rotated": false,
	"trimmed": false,
	"spriteSourceSize": {"x":0,"y":0,"w":160,"h":160},
	"sourceSize": {"w":160,"h":160},
	"pivot": {"x":0.5,"y":0.5}
},
"$down_off":
{
	"frame": {"x":160,"y":0,"w":160,"h":160},
	"rotated": false,
	"trimmed": false,
	"spriteSourceSize": {"x":0,"y":0,"w":160,"h":160},
	"sourceSize": {"w":160,"h":160},
	"pivot": {"x":0.5,"y":0.5}
},
"$downleft_firing-1":
{
	"frame": {"x":160,"y":160,"w":160,"h":160},
	"rotated": false,
	"trimmed": false,
	"spriteSourceSize": {"x":0,"y":0,"w":160,"h":160},
	"sourceSize": {"w":160,"h":160},
	"pivot": {"x":0.5,"y":0.5}
},
"$downleft_firing-2":
{
	"frame": {"x":160,"y":320,"w":160,"h":160},
	"rotated": false,
	"trimmed": false,
	"spriteSourceSize": {"x":0,"y":0,"w":160,"h":160},
	"sourceSize": {"w":160,"h":160},
	"pivot": {"x":0.5,"y":0.5}
},
"$downleft_firing-3":
{
	"frame": {"x":320,"y":0,"w":160,"h":160},
	"rotated": false,
	"trimmed": false,
	"spriteSourceSize": {"x":0,"y":0,"w":160,"h":160},
	"sourceSize": {"w":160,"h":160},
	"pivot": {"x":0.5,"y":0.5}
},
"$downleft_off":
{
	"frame": {"x":320,"y":160,"w":160,"h":160},
	"rotated": false,
	"trimmed": false,
	"spriteSourceSize": {"x":0,"y":0,"w":160,"h":160},
	"sourceSize": {"w":160,"h":160},
	"pivot": {"x":0.5,"y":0.5}
},
"$downright_firing-1":
{
	"frame": {"x":320,"y":320,"w":160,"h":160},
	"rotated": false,
	"trimmed": false,
	"spriteSourceSize": {"x":0,"y":0,"w":160,"h":160},
	"sourceSize": {"w":160,"h":160},
	"pivot": {"x":0.5,"y":0.5}
},
"$downright_firing-2":
{
	"frame": {"x":480,"y":0,"w":160,"h":160},
	"rotated": false,
	"trimmed": false,
	"spriteSourceSize": {"x":0,"y":0,"w":160,"h":160},
	"sourceSize": {"w":160,"h":160},
	"pivot": {"x":0.5,"y":0.5}
},
"$downright_firing-3":
{
	"frame": {"x":480,"y":160,"w":160,"h":160},
	"rotated": false,
	"trimmed": false,
	"spriteSourceSize": {"x":0,"y":0,"w":160,"h":160},
	"sourceSize": {"w":160,"h":160},
	"pivot": {"x":0.5,"y":0.5}
},
"$downright_off":
{
	"frame": {"x":480,"y":320,"w":160,"h":160},
	"rotated": false,
	"trimmed": false,
	"spriteSourceSize": {"x":0,"y":0,"w":160,"h":160},
	"sourceSize": {"w":160,"h":160},
	"pivot": {"x":0.5,"y":0.5}
},
"$left_firing-1":
{
	"frame": {"x":640,"y":0,"w":160,"h":160},
	"rotated": false,
	"trimmed": false,
	"spriteSourceSize": {"x":0,"y":0,"w":160,"h":160},
	"sourceSize": {"w":160,"h":160},
	"pivot": {"x":0.5,"y":0.5}
},
"$left_firing-2":
{
	"frame": {"x":640,"y":160,"w":160,"h":160},
	"rotated": false,
	"trimmed": false,
	"spriteSourceSize": {"x":0,"y":0,"w":160,"h":160},
	"sourceSize": {"w":160,"h":160},
	"pivot": {"x":0.5,"y":0.5}
},
"$left_firing-3":
{
	"frame": {"x":640,"y":320,"w":160,"h":160},
	"rotated": false,
	"trimmed": false,
	"spriteSourceSize": {"x":0,"y":0,"w":160,"h":160},
	"sourceSize": {"w":160,"h":160},
	"pivot": {"x":0.5,"y":0.5}
},
"$left_off":
{
	"frame": {"x":800,"y":0,"w":160,"h":160},
	"rotated": false,
	"trimmed": false,
	"spriteSourceSize": {"x":0,"y":0,"w":160,"h":160},
	"sourceSize": {"w":160,"h":160},
	"pivot": {"x":0.5,"y":0.5}
},
"$right_firing-1":
{
	"frame": {"x":800,"y":160,"w":160,"h":160},
	"rotated": false,
	"trimmed": false,
	"spriteSourceSize": {"x":0,"y":0,"w":160,"h":160},
	"sourceSize": {"w":160,"h":160},
	"pivot": {"x":0.5,"y":0.5}
},
"$right_firing-2":
{
	"frame": {"x":800,"y":320,"w":160,"h":160},
	"rotated": false,
	"trimmed": false,
	"spriteSourceSize": {"x":0,"y":0,"w":160,"h":160},
	"sourceSize": {"w":160,"h":160},
	"pivot": {"x":0.5,"y":0.5}
},
"$right_firing-3":
{
	"frame": {"x":960,"y":0,"w":160,"h":160},
	"rotated": false,
	"trimmed": false,
	"spriteSourceSize": {"x":0,"y":0,"w":160,"h":160},
	"sourceSize": {"w":160,"h":160},
	"pivot": {"x":0.5,"y":0.5}
},
"$right_off":
{
	"frame": {"x":960,"y":160,"w":160,"h":160},
	"rotated": false,
	"trimmed": false,
	"spriteSourceSize": {"x":0,"y":0,"w":160,"h":160},
	"sourceSize": {"w":160,"h":160},
	"pivot": {"x":0.5,"y":0.5}
},
"$up_firing-1":
{
	"frame": {"x":960,"y":320,"w":160,"h":160},
	"rotated": false,
	"trimmed": false,
	"spriteSourceSize": {"x":0,"y":0,"w":160,"h":160},
	"sourceSize": {"w":160,"h":160},
	"pivot": {"x":0.5,"y":0.5}
},
"$up_firing-2":
{
	"frame": {"x":1120,"y":0,"w":160,"h":160},
	"rotated": false,
	"trimmed": false,
	"spriteSourceSize": {"x":0,"y":0,"w":160,"h":160},
	"sourceSize": {"w":160,"h":160},
	"pivot": {"x":0.5,"y":0.5}
},
"$up_firing-3":
{
	"frame": {"x":1120,"y":160,"w":160,"h":160},
	"rotated": false,
	"trimmed": false,
	"spriteSourceSize": {"x":0,"y":0,"w":160,"h":160},
	"sourceSize": {"w":160,"h":160},
	"pivot": {"x":0.5,"y":0.5}
},
"$up_off":
{
	"frame": {"x":1120,"y":320,"w":160,"h":160},
	"rotated": false,
	"trimmed": false,
	"spriteSourceSize": {"x":0,"y":0,"w":160,"h":160},
	"sourceSize": {"w":160,"h":160},
	"pivot": {"x":0.5,"y":0.5}
},
"$upleft_firing-1":
{
	"frame": {"x":1280,"y":0,"w":160,"h":160},
	"rotated": false,
	"trimmed": false,
	"spriteSourceSize": {"x":0,"y":0,"w":160,"h":160},
	"sourceSize": {"w":160,"h":160},
	"pivot": {"x":0.5,"y":0.5}
},
"$upleft_firing-2":
{
	"frame": {"x":1280,"y":160,"w":160,"h":160},
	"rotated": false,
	"trimmed": false,
	"spriteSourceSize": {"x":0,"y":0,"w":160,"h":160},
	"sourceSize": {"w":160,"h":160},
	"pivot": {"x":0.5,"y":0.5}
},
"$upleft_firing-3":
{
	"frame": {"x":1280,"y":320,"w":160,"h":160},
	"rotated": false,
	"trimmed": false,
	"spriteSourceSize": {"x":0,"y":0,"w":160,"h":160},
	"sourceSize": {"w":160,"h":160},
	"pivot": {"x":0.5,"y":0.5}
},
"$upleft_off":
{
	"frame": {"x":1440,"y":0,"w":160,"h":160},
	"rotated": false,
	"trimmed": false,
	"spriteSourceSize": {"x":0,"y":0,"w":160,"h":160},
	"sourceSize": {"w":160,"h":160},
	"pivot": {"x":0.5,"y":0.5}
},
"$upright_firing-1":
{
	"frame": {"x":1600,"y":0,"w":160,"h":160},
	"rotated": false,
	"trimmed": false,
	"spriteSourceSize": {"x":0,"y":0,"w":160,"h":160},
	"sourceSize": {"w":160,"h":160},
	"pivot": {"x":0.5,"y":0.5}
},
"$upright_firing-2":
{
	"frame": {"x":1440,"y":160,"w":160,"h":160},
	"rotated": false,
	"trimmed": false,
	"spriteSourceSize": {"x":0,"y":0,"w":160,"h":160},
	"sourceSize": {"w":160,"h":160},
	"pivot": {"x":0.5,"y":0.5}
},
"$upright_firing-3":
{
	"frame": {"x":1440,"y":320,"w":160,"h":160},
	"rotated": false,
	"trimmed": false,
	"spriteSourceSize": {"x":0,"y":0,"w":160,"h":160},
	"sourceSize": {"w":160,"h":160},
	"pivot": {"x":0.5,"y":0.5}
},
"$upright_off":
{
	"frame": {"x":1600,"y":160,"w":160,"h":160},
	"rotated": false,
	"trimmed": false,
	"spriteSourceSize": {"x":0,"y":0,"w":160,"h":160},
	"sourceSize": {"w":160,"h":160},
	"pivot": {"x":0.5,"y":0.5}
}},
"meta": {
	"app": "http://www.codeandweb.com/texturepacker",
	"version": "1.0",
	"image": "pistol-d10.png",
	"format": "RGBA8888",
	"size": {"w":1760,"h":480},
	"scale": "1",
	"smartupdate": "$TexturePacker:SmartUpdate:86d548cbd9b5e4cc9472d21e5f461bd5:8d75cd749c1d79851880ee03a9563a15:b9ed9734941b499ece2d46c964939e1f$"
}
}
